[
  {
    "country": "Aruba",
    "aliases": [],
    "code": "ABW",
    "capital": "Oranjestad",
    "location": {
      "lat": 12,
      "long": -69
    },
    "flagCode": "AW",
    "colors": [
      "blue"
    ],
    "availablePrompts": ["name", "flag", "location"]
  },
  {
    "country": "Afghanistan",
    "aliases": [
      "Islamic Republic of Afghanistan"
    ],
    "code": "AFG",
    "capital": "Kabul",
    "location": {
      "lat": 33,
      "long": 66
    },
    "flagCode": "AF",
    "colors": [
      "red",
      "green",
      "black"
    ],
    "availablePrompts": ["name", "flag", "location"]
  },
  {
    "country": "Angola",
    "aliases": [
      "Republic of Angola"
    ],
    "code": "AGO",
    "capital": "Luanda",
    "location": {
      "lat": -12,
      "long": 18
    },
    "flagCode": "AO",
    "colors": [
      "black",
      "red"
    ],
    "availablePrompts": ["name", "flag", "location"]
  },
  {
    "country": "Anguilla",
    "aliases": [],
    "code": "AIA",
    "capital": "The Valley",
    "location": {
      "lat": 18,
      "long": -63
    },
    "flagCode": "AI",
    "colors": [
      "blue"
    ],
    "availablePrompts": ["name", "flag", "location"]
  },
  {
    "country": "Aland",
    "aliases": [
      "Åland"
    ],
    "code": "ALA",
    "capital": "Mariehamn",
    "location": {
      "lat": 60,
      "long": 20
    },
    "flagCode": "AX",
    "colors": [],
    "availablePrompts": ["name", "flag", "location"]
  },
  {
    "country": "Albania",
    "aliases": [
      "Republic of Albania"
    ],
    "code": "ALB",
    "capital": "Tirana",
    "location": {
      "lat": 41,
      "long": 20
    },
    "flagCode": "AL",
    "colors": [
      "red"
    ],
    "availablePrompts": ["name", "flag", "location"]
  },
  {
    "country": "Andorra",
    "aliases": [
      "Principality of Andorra"
    ],
    "code": "AND",
    "capital": "Andorra la Vella",
    "location": {
      "lat": 42,
      "long": 1
    },
    "flagCode": "AD",
    "colors": [
      "blue",
      "yellow",
      "red"
    ],
    "availablePrompts": ["name", "flag", "location"]
  },
  {
    "country": "United Arab Emirates",
    "aliases": [
      "UAE"
    ],
    "code": "ARE",
    "capital": "Abu Dhabi",
    "location": {
      "lat": 24,
      "long": 54
    },
    "flagCode": "AE",
    "colors": [
      "black",
      "white",
      "red",
      "green"
    ],
    "availablePrompts": ["name", "flag", "location"]
  },
  {
    "country": "Argentina",
    "aliases": [
      "Argentine Republic"
    ],
    "code": "ARG",
    "capital": "Buenos Aires",
    "location": {
      "lat": -34,
      "long": -64
    },
    "flagCode": "AR",
    "colors": [
      "blue",
      "white"
    ],
    "availablePrompts": ["name", "flag", "location"]
  },
  {
    "country": "Armenia",
    "aliases": [
      "Republic of Armenia"
    ],
    "code": "ARM",
    "capital": "Yerevan",
    "location": {
      "lat": 40,
      "long": 44
    },
    "flagCode": "AM",
    "colors": [
      "red",
      "blue",
      "orange"
    ],
    "availablePrompts": ["name", "flag", "location"]
  },
  {
    "country": "American Samoa",
    "aliases": [],
    "code": "ASM",
    "capital": "Pago Pago",
    "location": {
      "lat": -14,
      "long": -170
    },
    "flagCode": "AS",
    "colors": [
      "blue",
      "white"
    ],
    "availablePrompts": ["name", "flag", "location"]
  },
  {
    "country": "Antarctica",
    "aliases": [],
    "code": "ATA",
    "capital": "",
    "location": {
      "lat": -90,
      "long": 0
    },
    "flagCode": "AQ",
    "colors": [
      "blue",
      "white"
    ],
    "availablePrompts": ["name", "flag", "location"]
  },
  {
    "country": "French Southern Territories",
    "aliases": [],
    "code": "ATF",
    "capital": "Saint Pierre",
    "location": {
      "lat": -43,
      "long": 67
    },
    "flagCode": "TF",
    "colors": [
      "blue",
      "white"
    ],
    "availablePrompts": ["name", "flag", "location"]
  },
  {
    "country": "Antigua and Barbuda",
    "aliases": [
      "Antigua and Barbuda"
    ],
    "code": "ATG",
    "capital": "None (",
    "location": {
      "lat": 17,
      "long": -61
    },
    "flagCode": "AG",
    "colors": [
      "red",
      "black"
    ],
    "availablePrompts": ["name", "flag", "location"]
  },
  {
    "country": "Australia",
    "aliases": [
      "Commonwealth of Australia"
    ],
    "code": "AUS",
    "capital": "Canberra",
    "location": {
      "lat": -25,
      "long": 133
    },
    "flagCode": "AU",
    "colors": [
      "blue"
    ],
    "availablePrompts": ["name", "flag", "location"]
  },
  {
    "country": "Austria",
    "aliases": [
      "Republic of Austria"
    ],
    "code": "AUT",
    "capital": "Vienna",
    "location": {
      "lat": 47,
      "long": 13
    },
    "flagCode": "AT",
    "colors": [
      "red",
      "white"
    ],
    "availablePrompts": ["name", "flag", "location"]
  },
  {
    "country": "Azerbaijan",
    "aliases": [
      "Republic of Azerbaijan"
    ],
    "code": "AZE",
    "capital": "Baku",
    "location": {
      "lat": 40,
      "long": 47
    },
    "flagCode": "AZ",
    "colors": [
      "blue",
      "red",
      "green"
    ],
    "availablePrompts": ["name", "flag", "location"]
  },
  {
    "country": "Burundi",
    "aliases": [
      "Republic of Burundi"
    ],
    "code": "BDI",
    "capital": "Gitega",
    "location": {
      "lat": -3,
      "long": 30
    },
    "flagCode": "BI",
    "colors": [
      "red",
      "green"
    ],
    "availablePrompts": ["name", "flag", "location"]
  },
  {
    "country": "Belgium",
    "aliases": [
      "Kingdom of Belgium"
    ],
    "code": "BEL",
    "capital": "City of Brussels",
    "location": {
      "lat": 50,
      "long": 4
    },
    "flagCode": "BE",
    "colors": [
      "red",
      "black",
      "yellow"
    ],
    "availablePrompts": ["name", "flag", "location"]
  },
  {
    "country": "Benin",
    "aliases": [
      "Republic of Benin"
    ],
    "code": "BEN",
    "capital": "Porto-Novo",
    "location": {
      "lat": 6,
      "long": 2
    },
    "flagCode": "BJ",
    "colors": [
      "green",
      "yellow",
      "red"
    ],
    "availablePrompts": ["name", "flag", "location"]
  },
  {
    "country": "Bonaire",
    "aliases": [
      "Bonaire, Sint Eustatius and Saba"
    ],
    "code": "BES",
    "capital": "Kralendijk",
    "location": {
      "lat": 12,
      "long": -68
    },
    "flagCode": "NL",
    "colors": [
      "red",
      "white",
      "blue"
    ],
    "availablePrompts": [
      "name",
      "location"
    ]
  },
  {
    "country": "Burkina Faso",
    "aliases": [
      "Burkina Faso"
    ],
    "code": "BFA",
    "capital": "Ouagadougou",
    "location": {
      "lat": 12,
      "long": -1
    },
    "flagCode": "BF",
    "colors": [
      "red",
      "green"
    ],
    "availablePrompts": ["name", "flag", "location"]
  },
  {
    "country": "Bangladesh",
    "aliases": [
      "People's Republic of Bangladesh"
    ],
    "code": "BGD",
    "capital": "Dhaka",
    "location": {
      "lat": 24,
      "long": 90
    },
    "flagCode": "BD",
    "colors": [
      "green",
      "red"
    ],
    "availablePrompts": ["name", "flag", "location"]
  },
  {
    "country": "Bulgaria",
    "aliases": [
      "Republic of Bulgaria"
    ],
    "code": "BGR",
    "capital": "Sofia",
    "location": {
      "lat": 43,
      "long": 25
    },
    "flagCode": "BG",
    "colors": [],
    "availablePrompts": ["name", "flag", "location"]
  },
  {
    "country": "Bahrain",
    "aliases": [
      "Kingdom of Bahrain"
    ],
    "code": "BHR",
    "capital": "Manama",
    "location": {
      "lat": 26,
      "long": 50
    },
    "flagCode": "BH",
    "colors": [
      "red",
      "white"
    ],
    "availablePrompts": ["name", "flag", "location"]
  },
  {
    "country": "Bahamas",
    "aliases": [
      "Commonwealth of The Bahamas"
    ],
    "code": "BHS",
    "capital": "Nassau",
    "location": {
      "lat": 25,
      "long": -77
    },
    "flagCode": "BS",
    "colors": [
      "blue",
      "yellow"
    ],
    "availablePrompts": ["name", "flag", "location"]
  },
  {
    "country": "Bosnia and Herzegovina",
    "aliases": [],
    "code": "BIH",
    "capital": "Sarajevo",
    "location": {
      "lat": 44,
      "long": 18
    },
    "flagCode": "BA",
    "colors": [
      "blue",
      "yellow"
    ],
    "availablePrompts": ["name", "flag", "location"]
  },
  {
    "country": "Saint Barthelemy",
    "aliases": [
      "Saint Barthélemy"
    ],
    "code": "BLM",
    "capital": "Gustavia",
    "location": {
      "lat": 17,
      "long": -62
    },
    "flagCode": "FR",
    "colors": [
      "white",
      "red",
      "blue"
    ],
    "availablePrompts": ["name", "flag", "location"]
  },
  {
    "country": "Belarus",
    "aliases": [
      "Republic of Belarus"
    ],
    "code": "BLR",
    "capital": "Minsk",
    "location": {
      "lat": 53,
      "long": 27
    },
    "flagCode": "BY",
    "colors": [
      "red",
      "green"
    ],
    "availablePrompts": ["name", "flag", "location"]
  },
  {
    "country": "Belize",
    "aliases": [],
    "code": "BLZ",
    "capital": "Belmopan",
    "location": {
      "lat": 17,
      "long": -88
    },
    "flagCode": "BZ",
    "colors": [
      "blue"
    ],
    "availablePrompts": ["name", "flag", "location"]
  },
  {
    "country": "Bermuda",
    "aliases": [],
    "code": "BMU",
    "capital": "Hamilton",
    "location": {
      "lat": 32,
      "long": -64
    },
    "flagCode": "BM",
    "colors": [
      "red"
    ],
    "availablePrompts": ["name", "flag", "location"]
  },
  {
    "country": "Bolivia",
    "aliases": [
      "Plurinational State of Bolivia"
    ],
    "code": "BOL",
    "capital": "Sucre",
    "location": {
      "lat": -16,
      "long": -64
    },
    "flagCode": "BO",
    "colors": [
      "red",
      "yellow",
      "green"
    ],
    "availablePrompts": ["name", "flag", "location"]
  },
  {
    "country": "Brazil",
    "aliases": [
      "Federative Republic of Brazil"
    ],
    "code": "BRA",
    "capital": "Brasilia",
    "location": {
      "lat": -10,
      "long": -52
    },
    "flagCode": "BR",
    "colors": [
      "green",
      "yellow"
    ],
    "availablePrompts": ["name", "flag", "location"]
  },
  {
    "country": "Barbados",
    "aliases": [],
    "code": "BRB",
    "capital": "Bridgetown",
    "location": {
      "lat": 13,
      "long": -59
    },
    "flagCode": "BB",
    "colors": [
      "blue",
      "yellow"
    ],
    "availablePrompts": ["name", "flag", "location"]
  },
  {
    "country": "Brunei Darussalam",
    "aliases": [
      "Brunei Darussalam"
    ],
    "code": "BRN",
    "capital": "Bandar Seri Begawan",
    "location": {
      "lat": -4,
      "long": 114
    },
    "flagCode": "BN",
    "colors": [
      "yellow"
    ],
    "availablePrompts": ["name", "flag", "location"]
  },
  {
    "country": "Bhutan",
    "aliases": [
      "Kingdom of Bhutan"
    ],
    "code": "BTN",
    "capital": "Thimphu",
    "location": {
      "lat": 27,
      "long": 90
    },
    "flagCode": "BT",
    "colors": [
      "orange",
      "yellow"
    ],
    "availablePrompts": ["name", "flag", "location"]
  },
  {
    "country": "Botswana",
    "aliases": [
      "Republic of Botswana"
    ],
    "code": "BWA",
    "capital": "Gaborone",
    "location": {
      "lat": -24,
      "long": 25
    },
    "flagCode": "BW",
    "colors": [
      "blue"
    ],
    "availablePrompts": ["name", "flag", "location"]
  },
  {
    "country": "Central African Republic",
    "aliases": [
      "Central African Republic"
    ],
    "code": "CAF",
    "capital": "Bangui",
    "location": {
      "lat": 7,
      "long": 21
    },
    "flagCode": "CF",
    "colors": [
      "red",
      "green",
      "yellow",
      "white",
      "blue"
    ],
    "availablePrompts": ["name", "flag", "location"]
  },
  {
    "country": "Canada",
    "aliases": [],
    "code": "CAN",
    "capital": "Ottawa",
    "location": {
      "lat": 60,
      "long": -110
    },
    "flagCode": "CA",
    "colors": [
      "red",
      "white"
    ],
    "availablePrompts": ["name", "flag", "location"]
  },
  {
    "country": "Switzerland",
    "aliases": [
      "Swiss Confederation"
    ],
    "code": "CHE",
    "capital": "Bern",
    "location": {
      "lat": 46,
      "long": 8
    },
    "flagCode": "CH",
    "colors": [
      "red",
      "white"
    ],
    "availablePrompts": ["name", "flag", "location"]
  },
  {
    "country": "Chile",
    "aliases": [
      "Republic of Chile"
    ],
    "code": "CHL",
    "capital": "Santiago",
    "location": {
      "lat": -34,
      "long": -71
    },
    "flagCode": "CL",
    "colors": [
      "red",
      "white",
      "blue"
    ],
    "availablePrompts": ["name", "flag", "location"]
  },
  {
    "country": "China",
    "aliases": [
      "People's Republic of China"
    ],
    "code": "CHN",
    "capital": "Beijing",
    "location": {
      "lat": 35,
      "long": 103
    },
    "flagCode": "CN",
    "colors": [
      "red"
    ],
    "availablePrompts": ["name", "flag", "location"]
  },
  {
    "country": "Ivory Coast",
    "aliases": [
      "Republic of Côte d'Ivoire"
    ],
    "code": "CIV",
    "capital": "Yamoussoukro",
    "location": {
      "lat": 8,
      "long": -5
    },
    "flagCode": "CI",
    "colors": [
      "orange",
      "white",
      "green"
    ],
    "availablePrompts": ["name", "flag", "location"]
  },
  {
    "country": "Cameroon",
    "aliases": [
      "Republic of Cameroon"
    ],
    "code": "CMR",
    "capital": "Yaoundé",
    "location": {
      "lat": 6,
      "long": 12
    },
    "flagCode": "CM",
    "colors": [
      "green",
      "red",
      "yellow"
    ],
    "availablePrompts": ["name", "flag", "location"]
  },
  {
    "country": "Democratic Republic of the Congo",
    "aliases": [],
    "code": "COD",
    "capital": "Kinshasa",
    "location": {
      "lat": -3,
      "long": 24
    },
    "flagCode": "CD",
    "colors": [
      "blue"
    ],
    "availablePrompts": ["name", "flag", "location"]
  },
  {
    "country": "Republic of the Congo",
    "aliases": [],
    "code": "COG",
    "capital": "Brazzaville",
    "location": {
      "lat": -1,
      "long": 15
    },
    "flagCode": "CG",
    "colors": [
      "green",
      "yellow",
      "red"
    ],
    "availablePrompts": ["name", "flag", "location"]
  },
  {
    "country": "Cook Islands",
    "aliases": [
      "Cook Islands"
    ],
    "code": "COK",
    "capital": "Avarua",
    "location": {
      "lat": -21,
      "long": -159
    },
    "flagCode": "CK",
    "colors": [
      "blue"
    ],
    "availablePrompts": ["name", "flag", "location"]
  },
  {
    "country": "Colombia",
    "aliases": [
      "Republic of Colombia"
    ],
    "code": "COL",
    "capital": "Bogotá",
    "location": {
      "lat": 4,
      "long": -72
    },
    "flagCode": "CO",
    "colors": [
      "yellow",
      "blue",
      "red"
    ],
    "availablePrompts": ["name", "flag", "location"]
  },
  {
    "country": "Comoros",
    "aliases": [
      "Union of the Comoros"
    ],
    "code": "COM",
    "capital": "Moroni",
    "location": {
      "lat": -12,
      "long": 43
    },
    "flagCode": "KM",
    "colors": [
      "green"
    ],
    "availablePrompts": ["name", "flag", "location"]
  },
  {
    "country": "Cabo Verde",
    "aliases": [
      "Republic of Cabo Verde"
    ],
    "code": "CPV",
    "capital": "Praia",
    "location": {
      "lat": 15,
      "long": -23
    },
    "flagCode": "CV",
    "colors": [
      "blue"
    ],
    "availablePrompts": ["name", "flag", "location"]
  },
  {
    "country": "Costa Rica",
    "aliases": [
      "Republic of Costa Rica"
    ],
    "code": "CRI",
    "capital": "San José",
    "location": {
      "lat": 10,
      "long": -84
    },
    "flagCode": "CR",
    "colors": [
      "red"
    ],
    "availablePrompts": ["name", "flag", "location"]
  },
  {
    "country": "Cuba",
    "aliases": [
      "Republic of Cuba"
    ],
    "code": "CUB",
    "capital": "Havana",
    "location": {
      "lat": 22,
      "long": -80
    },
    "flagCode": "CU",
    "colors": [
      "blue",
      "white"
    ],
    "availablePrompts": ["name", "flag", "location"]
  },
  {
    "country": "Curaçao",
    "aliases": [
      "Curacao"
    ],
    "code": "CUW",
    "capital": "Willemstad",
    "location": {
      "lat": 12,
      "long": -69
    },
    "flagCode": "CW",
    "colors": [
      "blue"
    ],
    "availablePrompts": ["name", "flag", "location"]
  },
  {
    "country": "Cayman Islands",
    "aliases": [],
    "code": "CYM",
    "capital": "George Town",
    "location": {
      "lat": 19,
      "long": -81
    },
    "flagCode": "KY",
    "colors": [
      "blue"
    ],
    "availablePrompts": ["name", "flag", "location"]
  },
  {
    "country": "Cyprus",
    "aliases": [
      "Republic of Cyprus"
    ],
    "code": "CYP",
    "capital": "Nicosia",
    "location": {
      "lat": 35,
      "long": 33
    },
    "flagCode": "CY",
    "colors": [
      "orange",
      "white"
    ],
    "availablePrompts": ["name", "flag", "location"]
  },
  {
    "country": "Czech Republic",
    "aliases": [
      "Czech Republic"
    ],
    "code": "CZE",
    "capital": "Prague",
    "location": {
      "lat": 49,
      "long": 15
    },
    "flagCode": "CZ",
    "colors": [
      "blue",
      "white",
      "red"
    ],
    "availablePrompts": ["name", "flag", "location"]
  },
  {
    "country": "France",
    "aliases": [
      "French Republic"
    ],
    "code": "FRA",
    "capital": "Paris",
    "location": {
      "lat": 47,
      "long": 2
    },
    "flagCode": "FR",
    "colors": [
      "blue",
      "white",
      "red"
    ],
    "availablePrompts": ["name", "flag", "location"]
  },
  {
    "country": "Germany",
    "aliases": [
      "Federal Republic of Germany"
    ],
    "code": "DEU",
    "capital": "Berlin",
    "location": {
      "lat": 51,
      "long": 9
    },
    "flagCode": "DE",
    "colors": [
      "black",
      "red",
      "yellow"
    ],
    "availablePrompts": ["name", "flag", "location"]
  },
  {
    "country": "Djibouti",
    "aliases": [
      "Republic of Djibouti"
    ],
    "code": "DJI",
    "capital": "Djibouti City",
    "location": {
      "lat": 11,
      "long": 43
    },
    "flagCode": "DJ",
    "colors": [
      "white",
      "green",
      "blue"
    ],
    "availablePrompts": ["name", "flag", "location"]
  },
  {
    "country": "Dominica",
    "aliases": [
      "Commonwealth of Dominica"
    ],
    "code": "DMA",
    "capital": "Roseau",
    "location": {
      "lat": 15,
      "long": -61
    },
    "flagCode": "DM",
    "colors": [
      "green"
    ],
    "availablePrompts": ["name", "flag", "location"]
  },
  {
    "country": "Denmark",
    "aliases": [],
    "code": "DNK",
    "capital": "Copenhagen",
    "location": {
      "lat": 56,
      "long": 10
    },
    "flagCode": "DK",
    "colors": [
      "red",
      "white"
    ],
    "availablePrompts": ["name", "flag", "location"]
  },
  {
    "country": "Dominican Republic",
    "aliases": [
      "Dominican Republic"
    ],
    "code": "DOM",
    "capital": "Santo Domingo",
    "location": {
      "lat": 19,
      "long": -70
    },
    "flagCode": "DO",
    "colors": [
      "red",
      "blue",
      "white"
    ],
    "availablePrompts": ["name", "flag", "location"]
  },
  {
    "country": "Algeria",
    "aliases": [
      "People's Democratic Republic of Algeria"
    ],
    "code": "DZA",
    "capital": "Algiers",
    "location": {
      "lat": 28,
      "long": 2
    },
    "flagCode": "DZ",
    "colors": [
      "green",
      "white"
    ],
    "availablePrompts": ["name", "flag", "location"]
  },
  {
    "country": "Ecuador",
    "aliases": [
      "Republic of Ecuador"
    ],
    "code": "ECU",
    "capital": "Quito",
    "location": {
      "lat": -2,
      "long": -77
    },
    "flagCode": "EC",
    "colors": [
      "yellow"
    ],
    "availablePrompts": ["name", "flag", "location"]
  },
  {
    "country": "Egypt",
    "aliases": [
      "Arab Republic of Egypt"
    ],
    "code": "EGY",
    "capital": "Cairo",
    "location": {
      "lat": 26,
      "long": 30
    },
    "flagCode": "EG",
    "colors": [
      "black",
      "white",
      "red"
    ],
    "availablePrompts": ["name", "flag", "location"]
  },
  {
    "country": "Eritrea",
    "aliases": [
      "State of Eritrea"
    ],
    "code": "ERI",
    "capital": "Asmara",
    "location": {
      "lat": 15,
      "long": 39
    },
    "flagCode": "ER",
    "colors": [
      "red",
      "green",
      "blue"
    ],
    "availablePrompts": ["name", "flag", "location"]
  },
  {
    "country": "Western Sahara",
    "aliases": [],
    "code": "ESH",
    "capital": "",
    "location": {
      "lat": 24,
      "long": -14
    },
    "colors": [],
    "availablePrompts": ["name", "flag", "location"]
  },
  {
    "country": "Spain",
    "aliases": [
      "Kingdom of Spain"
    ],
    "code": "ESP",
    "capital": "Madrid",
    "location": {
      "lat": 40,
      "long": -4
    },
    "flagCode": "ES",
    "colors": [
      "yellow",
      "red"
    ],
    "availablePrompts": ["name", "flag", "location"]
  },
  {
    "country": "Estonia",
    "aliases": [
      "Republic of Estonia"
    ],
    "code": "EST",
    "capital": "Tallinn",
    "location": {
      "lat": 59,
      "long": 26
    },
    "flagCode": "EE",
    "colors": [
      "black",
      "blue",
      "white"
    ],
    "availablePrompts": ["name", "flag", "location"]
  },
  {
    "country": "Ethiopia",
    "aliases": [
      "Federal Democratic Republic of Ethiopia"
    ],
    "code": "ETH",
    "capital": "Addis Ababa",
    "location": {
      "lat": 9,
      "long": 38
    },
    "flagCode": "ET",
    "colors": [
      "blue",
      "yellow",
      "red",
      "green"
    ],
    "availablePrompts": ["name", "flag", "location"]
  },
  {
    "country": "Finland",
    "aliases": [
      "Republic of Finland"
    ],
    "code": "FIN",
    "capital": "Helsinki",
    "location": {
      "lat": 64,
      "long": 26
    },
    "flagCode": "FI",
    "colors": [
      "white"
    ],
    "availablePrompts": ["name", "flag", "location"]
  },
  {
    "country": "Fiji",
    "aliases": [
      "Republic of Fiji"
    ],
    "code": "FJI",
    "capital": "Suva",
    "location": {
      "lat": -18,
      "long": 179
    },
    "flagCode": "FJ",
    "colors": [
      "blue"
    ],
    "availablePrompts": ["name", "flag", "location"]
  },
  {
    "country": "Malvinas",
    "aliases": [
      "Falkland Islands (the) [Malvinas]"
    ],
    "code": "FLK",
    "capital": "Stanley",
    "location": {
      "lat": -51,
      "long": -59
    },
    "flagCode": "FK",
    "colors": [
      "blue"
    ],
    "availablePrompts": ["name", "flag", "location"]
  },
  {
    "country": "Faroe Islands",
    "aliases": [],
    "code": "FRO",
    "capital": "Tórshavn",
    "location": {
      "lat": 62,
      "long": -6
    },
    "flagCode": "FO",
    "colors": [
      "white",
      "red"
    ],
    "availablePrompts": ["name", "flag", "location"]
  },
  {
    "country": "Micronesia",
    "aliases": [
      "Federated States of Micronesia"
    ],
    "code": "FSM",
    "capital": "Palikir",
    "location": {
      "lat": -6,
      "long": -158
    },
    "flagCode": "FM",
    "colors": [
      "blue"
    ],
    "availablePrompts": ["flag", "name"]
  },
  {
    "country": "Gabon",
    "aliases": [
      "Gabonese Republic"
    ],
    "code": "GAB",
    "capital": "Libreville",
    "location": {
      "lat": -1,
      "long": 12
    },
    "flagCode": "GA",
    "colors": [
      "green",
      "yellow",
      "blue"
    ],
    "availablePrompts": ["name", "flag", "location"]
  },
  {
    "country": "United Kingdom",
    "aliases": [
      "United Kingdom of Great Britain and Northern Ireland"
    ],
    "code": "GBR",
    "capital": "London",
    "location": {
      "lat": 55,
      "long": -3
    },
    "flagCode": "GB",
    "colors": [
      "white",
      "red",
      "blue"
    ],
    "availablePrompts": ["name", "flag", "location"]
  },
  {
    "country": "Georgia",
    "aliases": [],
    "code": "GEO",
    "capital": "Tbilisi",
    "location": {
      "lat": 42,
      "long": 43
    },
    "flagCode": "GE",
    "colors": [
      "white",
      "red"
    ],
    "availablePrompts": ["name", "flag", "location"]
  },
  {
    "country": "Guernsey",
    "aliases": [],
    "code": "GGY",
    "capital": "Saint Peter Port",
    "location": {
      "lat": 49,
      "long": -2
    },
    "flagCode": "GG",
    "colors": [
      "white",
      "red",
      "yellow"
    ],
    "availablePrompts": ["name", "flag", "location"]
  },
  {
    "country": "Ghana",
    "aliases": [
      "Republic of Ghana"
    ],
    "code": "GHA",
    "capital": "Accra",
    "location": {
      "lat": 8,
      "long": -1
    },
    "flagCode": "GH",
    "colors": [
      "red",
      "green",
      "yellow"
    ],
    "availablePrompts": ["name", "flag", "location"]
  },
  {
    "country": "Gibraltar",
    "aliases": [],
    "code": "GIB",
    "capital": "",
    "location": {
      "lat": 36,
      "long": -5
    },
    "flagCode": "GI",
    "colors": [
      "white",
      "red"
    ],
    "availablePrompts": ["name", "flag", "location"]
  },
  {
    "country": "Guinea",
    "aliases": [
      "Republic of Guinea"
    ],
    "code": "GIN",
    "capital": "Conakry",
    "location": {
      "lat": 11,
      "long": -10
    },
    "flagCode": "GN",
    "colors": [
      "green",
      "yellow",
      "red"
    ],
    "availablePrompts": ["name", "flag", "location"]
  },
  {
    "country": "The Gambia",
    "aliases": [
      "Republic of The Gambia"
    ],
    "code": "GMB",
    "capital": "Banjul",
    "location": {
      "lat": 13,
      "long": -16
    },
    "flagCode": "GM",
    "colors": [
      "red",
      "green",
      "blue"
    ],
    "availablePrompts": ["name", "flag", "location"]
  },
  {
    "country": "Guinea-Bissau",
    "aliases": [
      "Republic of Guinea-Bissau"
    ],
    "code": "GNB",
    "capital": "Bissau",
    "location": {
      "lat": 12,
      "long": -15
    },
    "flagCode": "GW",
    "colors": [
      "green",
      "yellow",
      "red"
    ],
    "availablePrompts": ["name", "flag", "location"]
  },
  {
    "country": "Equatorial Guinea",
    "aliases": [
      "Republic of Equatorial Guinea"
    ],
    "code": "GNQ",
    "capital": "Malabo",
    "location": {
      "lat": -1,
      "long": -10
    },
    "flagCode": "GQ",
    "colors": [
      "green",
      "white",
      "red",
      "blue"
    ],
    "availablePrompts": ["name", "flag", "location"]
  },
  {
    "country": "Greece",
    "aliases": [
      "Hellenic Republic"
    ],
    "code": "GRC",
    "capital": "Athens",
    "location": {
      "lat": 39,
      "long": 22
    },
    "flagCode": "GR",
    "colors": [
      "white",
      "blue"
    ],
    "availablePrompts": ["name", "flag", "location"]
  },
  {
    "country": "Grenada",
    "aliases": [],
    "code": "GRD",
    "capital": "St. George's",
    "location": {
      "lat": 12,
      "long": -61
    },
    "flagCode": "GD",
    "colors": [
      "red",
      "green",
      "yellow"
    ],
    "availablePrompts": ["name", "flag", "location"]
  },
  {
    "country": "Greenland",
    "aliases": [],
    "code": "GRL",
    "capital": "Nuuk",
    "location": {
      "lat": 72,
      "long": -40
    },
    "flagCode": "GL",
    "colors": [
      "white",
      "red"
    ],
    "availablePrompts": ["name", "flag", "location"]
  },
  {
    "country": "Guatemala",
    "aliases": [
      "Republic of Guatemala"
    ],
    "code": "GTM",
    "capital": "Guatemala City",
    "location": {
      "lat": 15,
      "long": -90
    },
    "flagCode": "GT",
    "colors": [
      "blue",
      "white"
    ],
    "availablePrompts": ["name", "flag", "location"]
  },
  {
    "country": "Guam",
    "aliases": [],
    "code": "GUM",
    "capital": "Hagåtña",
    "location": {
      "lat": 13,
      "long": 144
    },
    "flagCode": "GU",
    "colors": [
      "blue"
    ],
    "availablePrompts": ["name", "flag", "location"]
  },
  {
    "country": "Guyana",
    "aliases": [
      "Co-operative Republic of Guyana"
    ],
    "code": "GUY",
    "capital": "Georgetown",
    "location": {
      "lat": 5,
      "long": -59
    },
    "flagCode": "GY",
    "colors": [
      "green",
      "yellow",
      "red"
    ],
    "availablePrompts": ["name", "flag", "location"]
  },
  {
    "country": "Hong Kong",
    "aliases": [],
    "code": "HKG",
    "capital": "",
    "location": {
      "lat": 22,
      "long": 114
    },
    "flagCode": "HK",
    "colors": [
      "white",
      "red"
    ],
    "availablePrompts": ["name", "flag", "location"]
  },
  {
    "country": "Heard Island and McDonald Islands",
    "aliases": [
      "HIMI"
    ],
    "code": "HMD",
    "capital": "",
    "location": {
      "lat": -53,
      "long": 73
    },
    "flagCode": "HM",
    "colors": [
      "blue"
    ],
    "availablePrompts": ["name", "flag", "location"]
  },
  {
    "country": "Honduras",
    "aliases": [
      "Republic of Honduras"
    ],
    "code": "HND",
    "capital": "Tegucigalpa",
    "location": {
      "lat": 15,
      "long": -86
    },
    "flagCode": "HN",
    "colors": [
      "blue"
    ],
    "availablePrompts": ["name", "flag", "location"]
  },
  {
    "country": "Croatia",
    "aliases": [
      "Republic of Croatia"
    ],
    "code": "HRV",
    "capital": "Zagreb",
    "location": {
      "lat": 45,
      "long": 15
    },
    "flagCode": "HR",
    "colors": [
      "white",
      "red",
      "blue"
    ],
    "availablePrompts": ["name", "flag", "location"]
  },
  {
    "country": "Haiti",
    "aliases": [
      "Republic of Haiti"
    ],
    "code": "HTI",
    "capital": "Port-au-Prince",
    "location": {
      "lat": 19,
      "long": -72
    },
    "flagCode": "HT",
    "colors": [
      "blue",
      "red"
    ],
    "availablePrompts": ["name", "flag", "location"]
  },
  {
    "country": "Hungary",
    "aliases": [
      "Hungary"
    ],
    "code": "HUN",
    "capital": "Budapest",
    "location": {
      "lat": 47,
      "long": 20
    },
    "flagCode": "HU",
    "colors": [
      "red",
      "white",
      "green"
    ],
    "availablePrompts": ["name", "flag", "location"]
  },
  {
    "country": "Indonesia",
    "aliases": [
      "Republic of Indonesia"
    ],
    "code": "IDN",
    "capital": "Jakarta",
    "location": {
      "lat": -5,
      "long": 120
    },
    "flagCode": "ID",
    "colors": [
      "white",
      "red"
    ],
    "availablePrompts": ["name", "flag", "location"]
  },
  {
    "country": "Isle of Man",
    "aliases": [],
    "code": "IMN",
    "capital": "Douglas",
    "location": {
      "lat": 54,
      "long": -4
    },
    "flagCode": "IM",
    "colors": [
      "red"
    ],
    "availablePrompts": ["name", "flag", "location"]
  },
  {
    "country": "India",
    "aliases": [
      "Republic of India"
    ],
    "code": "IND",
    "capital": "New Delhi",
    "location": {
      "lat": 21,
      "long": 78
    },
    "flagCode": "IN",
    "colors": [
      "orange",
      "white",
      "green"
    ],
    "availablePrompts": ["name", "flag", "location"]
  },
  {
    "country": "The British Indian Ocean Territory",
    "aliases": [],
    "code": "IOT",
    "capital": "",
    "location": {
      "lat": 7,
      "long": 72
    },
    "flagCode": "IO",
    "colors": [
      "blue",
      "white"
    ],
    "availablePrompts": []
  },
  {
    "country": "Ireland",
    "aliases": [
      "Ireland"
    ],
    "code": "IRL",
    "capital": "Dublin",
    "location": {
      "lat": 53,
      "long": -8
    },
    "flagCode": "IE",
    "colors": [
      "white",
      "green",
      "orange"
    ],
    "availablePrompts": ["name", "flag", "location"]
  },
  {
    "country": "Iran",
    "aliases": [
      "Islamic Republic of Iran"
    ],
    "code": "IRN",
    "capital": "Tehran",
    "location": {
      "lat": 32,
      "long": 53
    },
    "flagCode": "IR",
    "colors": [
      "green",
      "white",
      "red"
    ],
    "availablePrompts": ["name", "flag", "location"]
  },
  {
    "country": "Iraq",
    "aliases": [
      "Republic of Iraq"
    ],
    "code": "IRQ",
    "capital": "Baghdad",
    "location": {
      "lat": 33,
      "long": 44
    },
    "flagCode": "IQ",
    "colors": [
      "red",
      "white",
      "black"
    ],
    "availablePrompts": ["name", "flag", "location"]
  },
  {
    "country": "Iceland",
    "aliases": [],
    "code": "ISL",
    "capital": "Reykjavík",
    "location": {
      "lat": 65,
      "long": -18
    },
    "flagCode": "IS",
    "colors": [
      "blue",
      "red"
    ],
    "availablePrompts": ["name", "flag", "location"]
  },
  {
    "country": "Israel",
    "aliases": [
      "State of Israel"
    ],
    "code": "ISR",
    "capital": "Jerusalem",
    "location": {
      "lat": 31,
      "long": 35
    },
    "flagCode": "IL",
    "colors": [
      "white",
      "blue"
    ],
    "availablePrompts": ["name", "flag", "location"]
  },
  {
    "country": "Italy",
    "aliases": [
      "Italian Republic"
    ],
    "code": "ITA",
    "capital": "Rome",
    "location": {
      "lat": 43,
      "long": 12
    },
    "flagCode": "IT",
    "colors": [
      "red",
      "white",
      "green"
    ],
    "availablePrompts": ["name", "flag", "location"]
  },
  {
    "country": "Jamaica",
    "aliases": [],
    "code": "JAM",
    "capital": "Kingston",
    "location": {
      "lat": 18,
      "long": -77
    },
    "flagCode": "JM",
    "colors": [
      "green",
      "yellow",
      "black"
    ],
    "availablePrompts": ["name", "flag", "location"]
  },
  {
    "country": "Jersey",
    "aliases": [],
    "code": "JEY",
    "capital": "St Helier",
    "location": {
      "lat": 49,
      "long": -2
    },
    "flagCode": "JE",
    "colors": [
      "white",
      "red"
    ],
    "availablePrompts": ["name", "flag", "location"]
  },
  {
    "country": "Jordan",
    "aliases": [
      "Hashemite Kingdom of Jordan"
    ],
    "code": "JOR",
    "capital": "Amman",
    "location": {
      "lat": 31,
      "long": 36
    },
    "flagCode": "JO",
    "colors": [
      "black",
      "white",
      "green",
      "red"
    ],
    "availablePrompts": ["name", "flag", "location"]
  },
  {
    "country": "Japan",
    "aliases": [],
    "code": "JPN",
    "capital": "Tokyo",
    "location": {
      "lat": 36,
      "long": 138
    },
    "flagCode": "JP",
    "colors": [
      "white",
      "red"
    ],
    "availablePrompts": ["name", "flag", "location"]
  },
  {
    "country": "Kazakhstan",
    "aliases": [
      "Republic of Kazakhstan"
    ],
    "code": "KAZ",
    "capital": "Astana",
    "location": {
      "lat": 48,
      "long": 68
    },
    "flagCode": "KZ",
    "colors": [
      "blue"
    ],
    "availablePrompts": ["name", "flag", "location"]
  },
  {
    "country": "Kenya",
    "aliases": [
      "Republic of Kenya"
    ],
    "code": "KEN",
    "capital": "Nairobi",
    "location": {
      "lat": 1,
      "long": 38
    },
    "flagCode": "KE",
    "colors": [
      "red",
      "black",
      "green"
    ],
    "availablePrompts": ["name", "flag", "location"]
  },
  {
    "country": "Kyrgyzstan",
    "aliases": [
      "Kyrgyz Republic"
    ],
    "code": "KGZ",
    "capital": "Bishkek",
    "location": {
      "lat": 41,
      "long": 75
    },
    "flagCode": "KG",
    "colors": [
      "red"
    ],
    "availablePrompts": ["name", "flag", "location"]
  },
  {
    "country": "Cambodia",
    "aliases": [
      "Kingdom of Cambodia"
    ],
    "code": "KHM",
    "capital": "Phnom Penh",
    "location": {
      "lat": 12,
      "long": 105
    },
    "flagCode": "KH",
    "colors": [
      "blue",
      "red"
    ],
    "availablePrompts": ["name", "flag", "location"]
  },
  {
    "country": "Kiribati",
    "aliases": [
      "Republic of Kiribati"
    ],
    "code": "KIR",
    "capital": "Tarawa",
    "location": {
      "lat": -1,
      "long": -173
    },
    "flagCode": "KI",
    "colors": [
      "red",
      "white",
      "blue"
    ],
    "availablePrompts": ["name", "flag", "location"]
  },
  {
    "country": "Saint Kitts and Nevis",
    "aliases": [
      "Federation of Saint Kitts and Nevis"
    ],
    "code": "KNA",
    "capital": "Basseterre",
    "location": {
      "lat": 17,
      "long": -62
    },
    "flagCode": "KN",
    "colors": [
      "red",
      "black",
      "green"
    ],
    "availablePrompts": ["name", "flag", "location"]
  },
  {
    "country": "South Korea",
    "aliases": [
      "Republic of Korea"
    ],
    "code": "KOR",
    "capital": "Seoul",
    "location": {
      "lat": 36,
      "long": 128
    },
    "flagCode": "KR",
    "colors": [
      "white"
    ],
    "availablePrompts": ["name", "flag", "location"]
  },
  {
    "country": "Kuwait",
    "aliases": [
      "State of Kuwait"
    ],
    "code": "KWT",
    "capital": "Kuwait City",
    "location": {
      "lat": 29,
      "long": 47
    },
    "flagCode": "KW",
    "colors": [
      "black",
      "white",
      "red",
      "green"
    ],
    "availablePrompts": ["name", "flag", "location"]
  },
  {
    "country": "Laos",
    "aliases": [
      "Lao People's Democratic Republic"
    ],
    "code": "LAO",
    "capital": "Vientiane",
    "location": {
      "lat": 18,
      "long": 105
    },
    "flagCode": "LA",
    "colors": [
      "blue",
      "red"
    ],
    "availablePrompts": ["name", "flag", "location"]
  },
  {
    "country": "Lebanon",
    "aliases": [
      "Republic of Lebanon"
    ],
    "code": "LBN",
    "capital": "Beirut",
    "location": {
      "lat": 33,
      "long": 35
    },
    "flagCode": "LB",
    "colors": [
      "white",
      "red"
    ],
    "availablePrompts": ["name", "flag", "location"]
  },
  {
    "country": "Liberia",
    "aliases": [
      "Republic of Liberia"
    ],
    "code": "LBR",
    "capital": "Monrovia",
    "location": {
      "lat": 6,
      "long": -9
    },
    "flagCode": "LR",
    "colors": [
      "white",
      "red",
      "blue"
    ],
    "availablePrompts": ["name", "flag", "location"]
  },
  {
    "country": "Libya",
    "aliases": [
      "State of Libya"
    ],
    "code": "LBY",
    "capital": "Tripoli",
    "location": {
      "lat": 27,
      "long": 17
    },
    "flagCode": "LY",
    "colors": [
      "black",
      "red",
      "green"
    ],
    "availablePrompts": ["name", "flag", "location"]
  },
  {
    "country": "Saint Lucia",
    "aliases": [],
    "code": "LCA",
    "capital": "Castries",
    "location": {
      "lat": 13,
      "long": -60
    },
    "flagCode": "LC",
    "colors": [
      "blue"
    ],
    "availablePrompts": ["name", "flag", "location"]
  },
  {
    "country": "Liechtenstein",
    "aliases": [
      "Principality of Liechtenstein"
    ],
    "code": "LIE",
    "capital": "Vaduz",
    "location": {
      "lat": 47,
      "long": 9
    },
    "flagCode": "LI",
    "colors": [
      "blue",
      "red"
    ],
    "availablePrompts": ["name", "flag", "location"]
  },
  {
    "country": "Sri Lanka",
    "aliases": [
      "Democratic Socialist Republic of Sri Lanka"
    ],
    "code": "LKA",
    "capital": "Sri Jayawardenepura Kotte",
    "location": {
      "lat": 7,
      "long": 81
    },
    "flagCode": "LK",
    "colors": [
      "red",
      "yellow"
    ],
    "availablePrompts": ["name", "flag", "location"]
  },
  {
    "country": "Lesotho",
    "aliases": [
      "Kingdom of Lesotho"
    ],
    "code": "LSO",
    "capital": "Maseru",
    "location": {
      "lat": -29,
      "long": 28
    },
    "flagCode": "LS",
    "colors": [
      "blue",
      "white",
      "green"
    ],
    "availablePrompts": ["name", "flag", "location"]
  },
  {
    "country": "Lithuania",
    "aliases": [
      "Republic of Lithuania"
    ],
    "code": "LTU",
    "capital": "Vilnius",
    "location": {
      "lat": 55,
      "long": 24
    },
    "flagCode": "LT",
    "colors": [
      "red",
      "green",
      "yellow"
    ],
    "availablePrompts": ["name", "flag", "location"]
  },
  {
    "country": "Luxembourg",
    "aliases": [
      "Grand Duchy of Luxembourg"
    ],
    "code": "LUX",
    "capital": "Luxembourg",
    "location": {
      "lat": 49,
      "long": 6
    },
    "flagCode": "LU",
    "colors": [
      "red",
      "white",
      "blue"
    ],
    "availablePrompts": ["name", "flag", "location"]
  },
  {
    "country": "Latvia",
    "aliases": [
      "Republic of Latvia"
    ],
    "code": "LVA",
    "capital": "Riga",
    "location": {
      "lat": 57,
      "long": 25
    },
    "flagCode": "LV",
    "colors": [
      "red"
    ],
    "availablePrompts": ["name", "flag", "location"]
  },
  {
    "country": "Macao",
    "aliases": [
      "Macau"
    ],
    "code": "MAC",
    "capital": "",
    "location": {
      "lat": 22,
      "long": 113
    },
    "flagCode": "MO",
    "colors": [
      "green"
    ],
    "availablePrompts": ["name", "flag", "location"]
  },
  {
    "country": "Saint Martin",
    "aliases": [],
    "code": "MAF",
    "capital": "Marigot",
    "location": {
      "lat": -18,
      "long": -63
    },
    "flagCode": "FR",
    "colors": [
      "yellow",
      "green"
    ],
    "availablePrompts": ["name", "flag", "location"]
  },
  {
    "country": "Morocco",
    "aliases": [
      "Kingdom of Morocco"
    ],
    "code": "MAR",
    "capital": "Rabat",
    "location": {
      "lat": 32,
      "long": -6
    },
    "flagCode": "MA",
    "colors": [
      "red"
    ],
    "availablePrompts": ["name", "flag", "location"]
  },
  {
    "country": "Monaco",
    "aliases": [
      "Principality of Monaco"
    ],
    "code": "MCO",
    "capital": "Monaco",
    "location": {
      "lat": 43,
      "long": 7
    },
    "flagCode": "MC",
    "colors": [
      "white",
      "red"
    ],
    "availablePrompts": ["name", "flag", "location"]
  },
  {
    "country": "Moldova",
    "aliases": [
      "Republic of Moldova"
    ],
    "code": "MDA",
    "capital": "Chisinau",
    "location": {
      "lat": 47,
      "long": 29
    },
    "flagCode": "MD",
    "colors": [
      "red",
      "yellow",
      "blue"
    ],
    "availablePrompts": ["name", "flag", "location"]
  },
  {
    "country": "Madagascar",
    "aliases": [
      "Republic of Madagascar"
    ],
    "code": "MDG",
    "capital": "Antananarivo",
    "location": {
      "lat": -20,
      "long": 47
    },
    "flagCode": "MG",
    "colors": [
      "red",
      "white",
      "green"
    ],
    "availablePrompts": ["name", "flag", "location"]
  },
  {
    "country": "Maldives",
    "aliases": [
      "Republic of Maldives"
    ],
    "code": "MDV",
    "capital": "Male",
    "location": {
      "lat": 4,
      "long": 73
    },
    "flagCode": "MV",
    "colors": [
      "red",
      "green"
    ],
    "availablePrompts": ["name", "flag", "location"]
  },
  {
    "country": "Mexico",
    "aliases": [
      "United Mexican States"
    ],
    "code": "MEX",
    "capital": "Mexico City",
    "location": {
      "lat": 23,
      "long": -102
    },
    "flagCode": "MX",
    "colors": [
      "green",
      "red",
      "white"
    ],
    "availablePrompts": ["name", "flag", "location"]
  },
  {
    "country": "Marshall Islands",
    "aliases": [
      "Republic of the Marshall Islands"
    ],
    "code": "MHL",
    "capital": "Majuro",
    "location": {
      "lat": 9,
      "long": 169
    },
    "flagCode": "MH",
    "colors": [
      "blue"
    ],
    "availablePrompts": ["name", "flag", "location"]
  },
  {
    "country": "Macedonia",
    "aliases": [
      "Republic of North Macedonia"
    ],
    "code": "MKD",
    "capital": "Skopje",
    "location": {
      "lat": 42,
      "long": 22
    },
    "flagCode": "MK",
    "colors": [
      "red",
      "yellow"
    ],
    "availablePrompts": ["name", "flag", "location"]
  },
  {
    "country": "Mali",
    "aliases": [
      "Republic of Mali"
    ],
    "code": "MLI",
    "capital": "Bamako",
    "location": {
      "lat": 17,
      "long": -4
    },
    "flagCode": "ML",
    "colors": [
      "red",
      "green",
      "yellow"
    ],
    "availablePrompts": ["name", "flag", "location"]
  },
  {
    "country": "Malta",
    "aliases": [
      "Republic of Malta"
    ],
    "code": "MLT",
    "capital": "Valletta",
    "location": {
      "lat": 35,
      "long": 14
    },
    "flagCode": "MT",
    "colors": [
      "white",
      "red"
    ],
    "availablePrompts": ["name", "flag", "location"]
  },
  {
    "country": "Myanmar",
    "aliases": [
      "Republic of the Union of Myanmar"
    ],
    "code": "MMR",
    "capital": "Naypyidaw",
    "location": {
      "lat": 22,
      "long": 96
    },
    "flagCode": "MM",
    "colors": [
      "red",
      "yellow",
      "green"
    ],
    "availablePrompts": ["name", "flag", "location"]
  },
  {
    "country": "Montenegro",
    "aliases": [],
    "code": "MNE",
    "capital": "Podgorica",
    "location": {
      "lat": 42,
      "long": 19
    },
    "flagCode": "ME",
    "colors": [
      "red",
      "orange"
    ],
    "availablePrompts": ["name", "flag", "location"]
  },
  {
    "country": "Mongolia",
    "aliases": [],
    "code": "MNG",
    "capital": "Ulaanbaatar",
    "location": {
      "lat": 48,
      "long": 106
    },
    "flagCode": "MN",
    "colors": [
      "red",
      "blue"
    ],
    "availablePrompts": ["name", "flag", "location"]
  },
  {
    "country": "Northern Mariana Islands",
    "aliases": [
      "Commonwealth of the Northern Mariana Islands"
    ],
    "code": "MNP",
    "capital": "Saipan",
    "location": {
      "lat": 16,
      "long": 145
    },
    "flagCode": "MP",
    "colors": [
      "blue"
    ],
    "availablePrompts": ["name", "flag", "location"]
  },
  {
    "country": "Mozambique",
    "aliases": [
      "Republic of Mozambique"
    ],
    "code": "MOZ",
    "capital": "Maputo",
    "location": {
      "lat": -18,
      "long": 35
    },
    "flagCode": "MZ",
    "colors": [
      "red",
      "yellow",
      "green",
      "black"
    ],
    "availablePrompts": ["name", "flag", "location"]
  },
  {
    "country": "Mauritania",
    "aliases": [
      "Islamic Republic of Mauritania"
    ],
    "code": "MRT",
    "capital": "Nouakchott",
    "location": {
      "lat": 20,
      "long": -12
    },
    "flagCode": "MR",
    "colors": [
      "green",
      "red"
    ],
    "availablePrompts": ["name", "flag", "location"]
  },
  {
    "country": "Montserrat",
    "aliases": [],
    "code": "MSR",
    "capital": "Plymouth",
    "location": {
      "lat": 16,
      "long": -62
    },
    "flagCode": "MS",
    "colors": [
      "blue"
    ],
    "availablePrompts": ["name", "flag", "location"]
  },
  {
    "country": "Martinique",
    "aliases": [],
    "code": "MTQ",
    "capital": null,
    "location": {
      "lat": 14,
      "long": -61
    },
    "flagCode": "MQ",
    "colors": [
      "red",
      "green",
      "black"
    ],
    "availablePrompts": ["name", "flag", "location"]
  },
  {
    "country": "Mauritius",
    "aliases": [
      "Republic of Mauritius"
    ],
    "code": "MUS",
    "capital": "Port Louis",
    "location": {
      "lat": -20,
      "long": 57
    },
    "flagCode": "MU",
    "colors": [
      "red",
      "green",
      "blue",
      "yellow"
    ],
    "availablePrompts": ["name", "flag", "location"]
  },
  {
    "country": "Malawi",
    "aliases": [
      "Republic of Malawi"
    ],
    "code": "MWI",
    "capital": "Lilongwe",
    "location": {
      "lat": -13,
      "long": 34
    },
    "flagCode": "MW",
    "colors": [
      "red",
      "green",
      "black"
    ],
    "availablePrompts": ["name", "flag", "location"]
  },
  {
    "country": "Malaysia",
    "aliases": [],
    "code": "MYS",
    "capital": "Kuala Lumpur",
    "location": {
      "lat": 2,
      "long": 112
    },
    "flagCode": "MY",
    "colors": [
      "red",
      "white",
      "blue"
    ],
    "availablePrompts": ["name", "flag", "location"]
  },
  {
    "country": "Namibia",
    "aliases": [
      "Republic of Namibia"
    ],
    "code": "NAM",
    "capital": "Windhoek",
    "location": {
      "lat": -22,
      "long": 17
    },
    "flagCode": "NA",
    "colors": [
      "red",
      "green",
      "blue"
    ],
    "availablePrompts": ["name", "flag", "location"]
  },
  {
    "country": "New Caledonia",
    "aliases": [],
    "code": "NCL",
    "capital": "Noumea",
    "location": {
      "lat": -21,
      "long": 165
    },
    "flagCode": "NC",
    "colors": [
      "red",
      "green",
      "blue"
    ],
    "availablePrompts": ["name", "flag", "location"]
  },
  {
    "country": "Niger",
    "aliases": [
      "Republic of the Niger"
    ],
    "code": "NER",
    "capital": "Niamey",
    "location": {
      "lat": 16,
      "long": 8
    },
    "flagCode": "NE",
    "colors": [
      "orange",
      "white",
      "green"
    ],
    "availablePrompts": ["name", "flag", "location"]
  },
  {
    "country": "Norfolk Island",
    "aliases": [],
    "code": "NFK",
    "capital": "Kingston",
    "location": {
      "lat": -29,
      "long": 167
    },
    "flagCode": "NF",
    "colors": [
      "green",
      "white"
    ],
    "availablePrompts": ["flag", "name"]
  },
  {
    "country": "Nigeria",
    "aliases": [
      "Federal Republic of Nigeria"
    ],
    "code": "NGA",
    "capital": "Abuja",
    "location": {
      "lat": 8,
      "long": 10
    },
    "flagCode": "NG",
    "colors": [
      "green",
      "white"
    ],
    "availablePrompts": ["name", "flag", "location"]
  },
  {
    "country": "Nicaragua",
    "aliases": [
      "Republic of Nicaragua"
    ],
    "code": "NIC",
    "capital": "Managua",
    "location": {
      "lat": 13,
      "long": -85
    },
    "flagCode": "NI",
    "colors": [
      "blue",
      "white"
    ],
    "availablePrompts": ["name", "flag", "location"]
  },
  {
    "country": "Niue",
    "aliases": [
      "Niue"
    ],
    "code": "NIU",
    "capital": "Alofi",
    "location": {
      "lat": -19,
      "long": -169
    },
    "flagCode": "NU",
    "colors": [
      "yellow"
    ],
    "availablePrompts": ["name", "flag", "location"]
  },
  {
    "country": "Netherlands",
    "aliases": [
      "Kingdom of the Netherlands"
    ],
    "code": "NLD",
    "capital": "Amsterdam",
    "location": {
      "lat": 52,
      "long": 4
    },
    "flagCode": "NL",
    "colors": [
      "red",
      "white",
      "blue"
    ],
    "availablePrompts": ["name", "flag", "location"]
  },
  {
    "country": "Nepal",
    "aliases": [
      "Federal Democratic Republic of Nepal"
    ],
    "code": "NPL",
    "capital": "Kathmandu",
    "location": {
      "lat": 28,
      "long": 84
    },
    "flagCode": "NP",
    "colors": [
      "red",
      "white"
    ],
    "availablePrompts": ["name", "flag", "location"]
  },
  {
    "country": "Nauru",
    "aliases": [
      "Republic of Nauru"
    ],
    "code": "NRU",
    "capital": "(",
    "location": {
      "lat": 0,
      "long": 166
    },
    "flagCode": "NR",
    "colors": [
      "blue"
    ],
    "availablePrompts": ["name", "flag", "location"]
  },
  {
    "country": "New Zealand",
    "aliases": [
      "New Zealand"
    ],
    "code": "NZL",
    "capital": "Wellington",
    "location": {
      "lat": -42,
      "long": 173
    },
    "flagCode": "NZ",
    "colors": [
      "blue"
    ],
    "availablePrompts": ["name", "flag", "location"]
  },
  {
    "country": "Norway",
    "aliases": [
      "Kingdom of Norway"
    ],
    "code": "NOR",
    "capital": "Oslo",
    "location": {
      "lat": 61,
      "long": 8
    },
    "flagCode": "NO",
    "colors": [
      "red"
    ],
    "availablePrompts": ["name", "flag", "location"]
  },
  {
    "country": "Oman",
    "aliases": [
      "Sultanate of Oman"
    ],
    "code": "OMN",
    "capital": "Muscat",
    "location": {
      "lat": 21,
      "long": 57
    },
    "flagCode": "OM",
    "colors": [
      "red",
      "white",
      "green"
    ],
    "availablePrompts": ["name", "flag", "location"]
  },
  {
    "country": "Pakistan",
    "aliases": [
      "Islamic Republic of Pakistan"
    ],
    "code": "PAK",
    "capital": "Islamabad",
    "location": {
      "lat": 30,
      "long": 70
    },
    "flagCode": "PK",
    "colors": [
      "green",
      "white"
    ],
    "availablePrompts": ["name", "flag", "location"]
  },
  {
    "country": "Panama",
    "aliases": [
      "Republic of Panama"
    ],
    "code": "PAN",
    "capital": "Panama City",
    "location": {
      "lat": 9,
      "long": -80
    },
    "flagCode": "PA",
    "colors": [
      "white",
      "blue",
      "red"
    ],
    "availablePrompts": ["name", "flag", "location"]
  },
  {
    "country": "Pitcairn",
    "aliases": [],
    "code": "PCN",
    "capital": "Adamstown",
    "location": {
      "lat": -25,
      "long": -130
    },
    "flagCode": "PN",
    "colors": [
      "blue"
    ],
    "availablePrompts": ["name", "flag", "location"]
  },
  {
    "country": "Peru",
    "aliases": [
      "Republic of Peru"
    ],
    "code": "PER",
    "capital": "Lima",
    "location": {
      "lat": -10,
      "long": -76
    },
    "flagCode": "PE",
    "colors": [
      "red",
      "white"
    ],
    "availablePrompts": ["name", "flag", "location"]
  },
  {
    "country": "Philippines",
    "aliases": [
      "Republic of the Philippines"
    ],
    "code": "PHL",
    "capital": "Manila",
    "location": {
      "lat": 13,
      "long": 122
    },
    "flagCode": "PH",
    "colors": [
      "red",
      "white",
      "blue"
    ],
    "availablePrompts": ["name", "flag", "location"]
  },
  {
    "country": "Palau",
    "aliases": [
      "Republic of Palau"
    ],
    "code": "PLW",
    "capital": "Ngerulmud",
    "location": {
      "lat": 7,
      "long": 134
    },
    "flagCode": "PW",
    "colors": [
      "blue",
      "yellow"
    ],
    "availablePrompts": ["name", "flag", "location"]
  },
  {
    "country": "Papua New Guinea",
    "aliases": [
      "Independent State of Papua New Guinea"
    ],
    "code": "PNG",
    "capital": "Port Moresby",
    "location": {
      "lat": -6,
      "long": 147
    },
    "flagCode": "PG",
    "colors": [
      "black",
      "red"
    ],
    "availablePrompts": ["name", "flag", "location"]
  },
  {
    "country": "Poland",
    "aliases": [
      "Republic of Poland"
    ],
    "code": "POL",
    "capital": "Warsaw",
    "location": {
      "lat": 52,
      "long": 20
    },
    "flagCode": "PL",
    "colors": [
      "white",
      "red"
    ],
    "availablePrompts": ["name", "flag", "location"]
  },
  {
    "country": "Puerto Rico",
    "aliases": [],
    "code": "PRI",
    "capital": "San Juan",
    "location": {
      "lat": 18,
      "long": -66
    },
    "flagCode": "PR",
    "colors": [
      "blue",
      "white",
      "red"
    ],
    "availablePrompts": ["name", "flag", "location"]
  },
  {
    "country": "North Korea",
    "aliases": [
      "Democratic People's Republic of Korea"
    ],
    "code": "PRK",
    "capital": "Pyongyang",
    "location": {
      "lat": 40,
      "long": 127
    },
    "flagCode": "KP",
    "colors": [
      "red",
      "blue"
    ],
    "availablePrompts": ["name", "flag", "location"]
  },
  {
    "country": "Portugal",
    "aliases": [
      "Portuguese Republic"
    ],
    "code": "PRT",
    "capital": "Lisbon",
    "location": {
      "lat": 39,
      "long": -8
    },
    "flagCode": "PT",
    "colors": [
      "red",
      "green"
    ],
    "availablePrompts": ["name", "flag", "location"]
  },
  {
    "country": "Paraguay",
    "aliases": [
      "Republic of Paraguay"
    ],
    "code": "PRY",
    "capital": "Asuncion",
    "location": {
      "lat": -23,
      "long": -58
    },
    "flagCode": "PY",
    "colors": [
      "blue",
      "white",
      "red"
    ],
    "availablePrompts": ["name", "flag", "location"]
  },
  {
    "country": "Palestine",
    "aliases": [
      "State of Palestine"
    ],
    "code": "PSE",
    "capital": "Jerusalem",
    "location": {
      "lat": 32,
      "long": 35
    },
    "flagCode": "PS",
    "colors": [
      "red",
      "white",
      "black",
      "green"
    ],
    "availablePrompts": ["name", "flag", "location"]
  },
  {
    "country": "French Polynesia",
    "aliases": [],
    "code": "PYF",
    "capital": "Papeete",
    "location": {
      "lat": -17,
      "long": -149
    },
    "flagCode": "PF",
    "colors": [
      "red",
      "white"
    ],
    "availablePrompts": ["name", "flag", "location"]
  },
  {
    "country": "Qatar",
    "aliases": [
      "State of Qatar"
    ],
    "code": "QAT",
    "capital": "Doha",
    "location": {
      "lat": 25,
      "long": 51
    },
    "flagCode": "QA",
    "colors": [
      "red",
      "white"
    ],
    "availablePrompts": ["name", "flag", "location"]
  },
  {
    "country": "Romania",
    "aliases": [],
    "code": "ROU",
    "capital": "Bucharest",
    "location": {
      "lat": 46,
      "long": 25
    },
    "flagCode": "RO",
    "colors": [
      "blue",
      "yellow",
      "red"
    ],
    "availablePrompts": ["name", "flag", "location"]
  },
  {
    "country": "Russia",
    "aliases": [
      "Russian Federation"
    ],
    "code": "RUS",
    "capital": "Moscow",
    "location": {
      "lat": 66,
      "long": 94
    },
    "flagCode": "RU",
    "colors": [
      "white",
      "blue",
      "red"
    ],
    "availablePrompts": ["name", "flag", "location"]
  },
  {
    "country": "Rwanda",
    "aliases": [
      "Republic of Rwanda"
    ],
    "code": "RWA",
    "capital": "Kigali",
    "location": {
      "lat": -2,
      "long": 30
    },
    "flagCode": "RW",
    "colors": [
      "blue",
      "green",
      "yellow"
    ],
    "availablePrompts": ["name", "flag", "location"]
  },
  {
    "country": "Saudi Arabia",
    "aliases": [
      "Kingdom of Saudi Arabia"
    ],
    "code": "SAU",
    "capital": "Riyadh",
    "location": {
      "lat": 24,
      "long": 45
    },
    "flagCode": "SA",
    "colors": [
      "green"
    ],
    "availablePrompts": ["name", "flag", "location"]
  },
  {
    "country": "Sudan",
    "aliases": [
      "Republic of Sudan"
    ],
    "code": "SDN",
    "capital": "Khartoum",
    "location": {
      "lat": 15,
      "long": 32
    },
    "flagCode": "SD",
    "colors": [
      "red",
      "white",
      "black",
      "green"
    ],
    "availablePrompts": ["name", "flag", "location"]
  },
  {
    "country": "Senegal",
    "aliases": [
      "Republic of Senegal"
    ],
    "code": "SEN",
    "capital": "Dakar",
    "location": {
      "lat": 14,
      "long": -14
    },
    "flagCode": "SN",
    "colors": [
      "green",
      "yellow",
      "red"
    ],
    "availablePrompts": ["name", "flag", "location"]
  },
  {
    "country": "Singapore",
    "aliases": [
      "Republic of Singapore"
    ],
    "code": "SGP",
    "capital": "Singapore",
    "location": {
      "lat": -1,
      "long": 103
    },
    "flagCode": "SG",
    "colors": [
      "white",
      "red"
    ],
    "availablePrompts": ["name", "flag", "location"]
  },
  {
    "country": "South Georgia and the South Sandwich Islands",
    "aliases": [],
    "code": "SGS",
    "capital": "King Edward Point",
    "location": {
      "lat": -54,
      "long": -36
    },
    "flagCode": "GS",
    "colors": [
      "blue"
    ],
    "availablePrompts": ["name", "flag", "location"]
  },
  {
    "country": "Saint Helena, Ascension and Tristan da Cunha",
    "aliases": [],
    "code": "SHN",
    "capital": "Jamestown",
    "location": {
      "lat": -15,
      "long": -5
    },
    "flagCode": "SH",
    "colors": [
      "blue"
    ],
    "availablePrompts": ["name", "flag", "location"]
  },
  {
    "country": "Solomon Islands",
    "aliases": [],
    "code": "SLB",
    "capital": "Honiara",
    "location": {
      "lat": -8,
      "long": 159
    },
    "flagCode": "SB",
    "colors": [
      "green",
      "blue"
    ],
    "availablePrompts": ["name", "flag", "location"]
  },
  {
    "country": "Sierra Leone",
    "aliases": [
      "Republic of Sierra Leone"
    ],
    "code": "SLE",
    "capital": "Freetown",
    "location": {
      "lat": 8,
      "long": -12
    },
    "flagCode": "SL",
    "colors": [
      "blue",
      "white",
      "green"
    ],
    "availablePrompts": ["name", "flag", "location"]
  },
  {
    "country": "El Salvador",
    "aliases": [
      "Republic of El Salvador"
    ],
    "code": "SLV",
    "capital": "San Salvador",
    "location": {
      "lat": 13,
      "long": -89
    },
    "flagCode": "SV",
    "colors": [
      "blue",
      "white"
    ],
    "availablePrompts": ["name", "flag", "location"]
  },
  {
    "country": "San Marino",
    "aliases": [
      "Republic of San Marino"
    ],
    "code": "SMR",
    "capital": "City of San Marino",
    "location": {
      "lat": 43,
      "long": 12
    },
    "flagCode": "SM",
    "colors": [
      "white",
      "blue"
    ],
    "availablePrompts": ["name", "flag", "location"]
  },
  {
    "country": "Somalia",
    "aliases": [
      "Federal Republic of Somalia"
    ],
    "code": "SOM",
    "capital": "Mogadishu",
    "location": {
      "lat": 10,
      "long": 49
    },
    "flagCode": "SO",
    "colors": [
      "blue"
    ],
    "availablePrompts": ["name", "flag", "location"]
  },
  {
    "country": "Saint Pierre and Miquelon",
    "aliases": [],
    "code": "SPM",
    "capital": "Saint-Pierre",
    "location": {
      "lat": 46,
      "long": -56
    },
    "flagCode": "FR",
    "colors": [
      "blue",
      "white",
      "red"
    ],
    "availablePrompts": ["name", "flag", "location"]
  },
  {
    "country": "Serbia",
    "aliases": [
      "Republic of Serbia"
    ],
    "code": "SRB",
    "capital": "Belgrade",
    "location": {
      "lat": 44,
      "long": 21
    },
    "flagCode": "RS",
    "colors": [
      "blue",
      "white",
      "red"
    ],
    "availablePrompts": ["name", "flag", "location"]
  },
  {
    "country": "South Sudan",
    "aliases": [
      "Republic of South Sudan"
    ],
    "code": "SSD",
    "capital": "Juba",
    "location": {
      "lat": 8,
      "long": 30
    },
    "flagCode": "SS",
    "colors": [
      "red",
      "white",
      "black",
      "green",
      "blue"
    ],
    "availablePrompts": ["name", "flag", "location"]
  },
  {
    "country": "Sao Tome and Principe",
    "aliases": [
      "São Tomé and Príncipe",
      "Democratic Republic of São Tomé and Príncipe"
    ],
    "code": "STP",
    "capital": "São Tomé",
    "location": {
      "lat": 0,
      "long": 6
    },
    "flagCode": "ST",
    "colors": [
      "green",
      "yellow",
      "red"
    ],
    "availablePrompts": ["name", "flag", "location"]
  },
  {
    "country": "Republic of Suriname",
    "aliases": [
      "Republic of Suriname"
    ],
    "code": "SUR",
    "capital": "Paramaribo",
    "location": {
      "lat": 4,
      "long": -56
    },
    "flagCode": "SR",
    "colors": [
      "green",
      "red"
    ],
    "availablePrompts": ["name", "flag", "location"]
  },
  {
    "country": "Slovakia",
    "aliases": [
      "Slovak Republic"
    ],
    "code": "SVK",
    "capital": "Bratislava",
    "location": {
      "lat": 48,
      "long": 19
    },
    "flagCode": "SK",
    "colors": [
      "white",
      "red",
      "blue"
    ],
    "availablePrompts": ["name", "flag", "location"]
  },
  {
    "country": "Slovenia",
    "aliases": [
      "Republic of Slovenia"
    ],
    "code": "SVN",
    "capital": "Ljubljana",
    "location": {
      "lat": 46,
      "long": 14
    },
    "flagCode": "SI",
    "colors": [
      "white",
      "red",
      "blue"
    ],
    "availablePrompts": ["name", "flag", "location"]
  },
  {
    "country": "Sweden",
    "aliases": [
      "Kingdom of Sweden"
    ],
    "code": "SWE",
    "capital": "Stockholm",
    "location": {
      "lat": 63,
      "long": 16
    },
    "flagCode": "SE",
    "colors": [
      "blue",
      "yellow"
    ],
    "availablePrompts": ["name", "flag", "location"]
  },
  {
    "country": "Eswatini",
    "aliases": [
      "Kingdom of Eswatini"
    ],
    "code": "SWZ",
    "capital": "Mbabane",
    "location": {
      "lat": -26,
      "long": 31
    },
    "flagCode": "SZ",
    "colors": [
      "blue",
      "red",
      "yellow"
    ],
    "availablePrompts": ["name", "flag", "location"]
  },
  {
    "country": "Saint Martin",
    "aliases": [],
    "code": "SXM",
    "capital": "Philipsburg",
    "location": {
      "lat": 18,
      "long": -63
    },
    "flagCode": "SX",
    "colors": [
      "yellow",
      "green"
    ],
    "availablePrompts": ["name", "flag", "location"]
  },
  {
    "country": "Seychelles",
    "aliases": [
      "Republic of Seychelles"
    ],
    "code": "SYC",
    "capital": "Victoria",
    "location": {
      "lat": -4,
      "long": 55
    },
    "flagCode": "SC",
    "colors": [
      "red",
      "white",
      "blue",
      "yellow",
      "greem"
    ],
    "availablePrompts": ["name", "flag", "location"]
  },
  {
    "country": "Syria",
    "aliases": [
      "Syrian Arab Republic"
    ],
    "code": "SYR",
    "capital": "Damascus",
    "location": {
      "lat": 35,
      "long": 38
    },
    "flagCode": "SY",
    "colors": [
      "green",
      "white",
      "black"
    ],
    "availablePrompts": ["name", "flag", "location"]
  },
  {
    "country": "Turks and Caicos Islands",
    "aliases": [],
    "code": "TCA",
    "capital": "Grand Turk (Cockburn Town)",
    "location": {
      "lat": 21,
      "long": -71
    },
    "flagCode": "TC",
    "colors": [
      "blue"
    ],
    "availablePrompts": ["name", "flag", "location"]
  },
  {
    "country": "Chad",
    "aliases": [
      "Republic of Chad"
    ],
    "code": "TCD",
    "capital": "N'Djamena",
    "location": {
      "lat": 15,
      "long": 19
    },
    "flagCode": "TD",
    "colors": [
      "blue",
      "yellow",
      "red"
    ],
    "availablePrompts": ["name", "flag", "location"]
  },
  {
    "country": "Togo",
    "aliases": [
      "Togolese Republic"
    ],
    "code": "TGO",
    "capital": "Lomé",
    "location": {
      "lat": 8,
      "long": 1
    },
    "flagCode": "TG",
    "colors": [
      "green",
      "yellow"
    ],
    "availablePrompts": ["name", "flag", "location"]
  },
  {
    "country": "Thailand",
    "aliases": [
      "Kingdom of Thailand"
    ],
    "code": "THA",
    "capital": "Bangkok",
    "location": {
      "lat": 15,
      "long": 101
    },
    "flagCode": "TH",
    "colors": [
      "red",
      "white",
      "blue"
    ],
    "availablePrompts": ["name", "flag", "location"]
  },
  {
    "country": "Tajikistan",
    "aliases": [
      "Republic of Tajikistan"
    ],
    "code": "TJK",
    "capital": "Dushanbe",
    "location": {
      "lat": 39,
      "long": 71
    },
    "flagCode": "TJ",
    "colors": [
      "red",
      "white",
      "green"
    ],
    "availablePrompts": ["name", "flag", "location"]
  },
  {
    "country": "Tokelau",
    "aliases": [],
    "code": "TKL",
    "capital": "None",
    "location": {
      "lat": -9,
      "long": -171
    },
    "flagCode": "TK",
    "colors": [
      "blue",
      "yellow"
    ],
    "availablePrompts": ["name", "flag", "location"]
  },
  {
    "country": "Turkmenistan",
    "aliases": [],
    "code": "TKM",
    "capital": "Ashgabat",
    "location": {
      "lat": 39,
      "long": 60
    },
    "flagCode": "TM",
    "colors": [
      "green"
    ],
    "availablePrompts": ["name", "flag", "location"]
  },
  {
    "country": "Timor-Leste",
    "aliases": [
      "Democratic Republic of Timor-Leste"
    ],
    "code": "TLS",
    "capital": "Dili",
    "location": {
      "lat": -8,
      "long": 125
    },
    "flagCode": "TL",
    "colors": [
      "red"
    ],
    "availablePrompts": ["name", "flag", "location"]
  },
  {
    "country": "Tonga",
    "aliases": [
      "Kingdom of Tonga"
    ],
    "code": "TON",
    "capital": "Nuku'alofa",
    "location": {
      "lat": -20,
      "long": -175
    },
    "flagCode": "TO",
    "colors": [
      "red"
    ],
    "availablePrompts": ["name", "flag", "location"]
  },
  {
    "country": "Trinidad and Tobago",
    "aliases": [
      "Republic of Trinidad and Tobago"
    ],
    "code": "TTO",
    "capital": "Port of Spain",
    "location": {
      "lat": 10,
      "long": -61
    },
    "flagCode": "TT",
    "colors": [
      "red",
      "black"
    ],
    "availablePrompts": ["name", "flag", "location"]
  },
  {
    "country": "Tunisia",
    "aliases": [
      "Republic of Tunisia"
    ],
    "code": "TUN",
    "capital": "Tunis",
    "location": {
      "lat": 34,
      "long": 9
    },
    "flagCode": "TN",
    "colors": [
      "red",
      "white"
    ],
    "availablePrompts": ["name", "flag", "location"]
  },
  {
    "country": "Turkiye",
    "aliases": [
      "Republic of Türkiye",
      "Turkey",
      "Türkiye"
    ],
    "code": "TUR",
    "capital": "Ankara",
    "location": {
      "lat": 39,
      "long": 32
    },
    "flagCode": "TR",
    "colors": [
      "red",
      "white"
    ],
    "availablePrompts": ["name", "flag", "location"]
  },
  {
    "country": "Tuvalu",
    "aliases": [],
    "code": "TUV",
    "capital": "Funafuti",
    "location": {
      "lat": -8,
      "long": 179
    },
    "flagCode": "TV",
    "colors": [
      "blue"
    ],
    "availablePrompts": ["name", "flag", "location"]
  },
  {
    "country": "Taiwan",
    "aliases": [
      "Republic of China",
      "ROC"
    ],
    "code": "TWN",
    "capital": "Taipei",
    "location": {
      "lat": 24,
      "long": 121
    },
    "flagCode": "TW",
    "colors": [
      "red",
      "blue"
    ],
    "availablePrompts": ["name", "flag", "location"]
  },
  {
    "country": "Tanzania",
    "aliases": [
      "United Republic of Tanzania"
    ],
    "code": "TZA",
    "capital": "Dodoma",
    "location": {
      "lat": -6,
      "long": 35
    },
    "flagCode": "TZ",
    "colors": [
      "green",
      "black",
      "blue"
    ],
    "availablePrompts": ["name", "flag", "location"]
  },
  {
    "country": "Uganda",
    "aliases": [
      "Republic of Uganda"
    ],
    "code": "UGA",
    "capital": "Kampala",
    "location": {
      "lat": 1,
      "long": 32
    },
    "flagCode": "UG",
    "colors": [
      "black",
      "yellow",
      "red"
    ],
    "availablePrompts": ["name", "flag", "location"]
  },
  {
    "country": "Ukraine",
    "aliases": [
      "Ukraine"
    ],
    "code": "UKR",
    "capital": "Kyiv",
    "location": {
      "lat": 50,
      "long": 30
    },
    "flagCode": "UA",
    "colors": [
      "blue",
      "yellow"
    ],
    "availablePrompts": ["name", "flag", "location"]
  },
  {
    "country": "Uruguay",
    "aliases": [
      "Oriental Republic of Uruguay"
    ],
    "code": "URY",
    "capital": "Montevideo",
    "location": {
      "lat": -33,
      "long": -57
    },
    "flagCode": "UY",
    "colors": [
      "white",
      "blue"
    ],
    "availablePrompts": ["name", "flag", "location"]
  },
  {
    "country": "United States of America",
    "aliases": [
      "USA"
    ],
    "code": "USA",
    "capital": "Washington, D.C.",
    "location": {
      "lat": 40,
      "long": -100
    },
    "flagCode": "US",
    "colors": [
      "red",
      "white",
      "blue"
    ],
    "availablePrompts": ["name", "flag", "location"]
  },
  {
    "country": "Uzbekistan",
    "aliases": [
      "Republic of Uzbekistan"
    ],
    "code": "UZB",
    "capital": "Tashkent",
    "location": {
      "lat": 42,
      "long": 64
    },
    "flagCode": "UZ",
    "colors": [
      "blue",
      "white",
      "green"
    ],
    "availablePrompts": ["name", "flag", "location"]
  },
  {
    "country": "Vatican City",
    "aliases": [
      "The Holy See"
    ],
    "code": "VAT",
    "capital": "",
    "location": {
      "lat": 41,
      "long": 12
    },
    "flagCode": "VA",
    "colors": [
      "white",
      "yellow"
    ],
    "availablePrompts": ["name", "flag", "location"]
  },
  {
    "country": "Saint Vincent",
    "aliases": [
      "Saint Vincent and the Grenadines"
    ],
    "code": "VCT",
    "capital": "Kingstown",
    "location": {
      "lat": 13,
      "long": -61
    },
    "flagCode": "VC",
    "colors": [
      "yellow",
      "green",
      "blue"
    ],
    "availablePrompts": ["name", "flag", "location"]
  },
  {
    "country": "Venezuela",
    "aliases": [
      "Bolivarian Republic of Venezuela"
    ],
    "code": "VEN",
    "capital": "Caracas",
    "location": {
      "lat": 7,
      "long": -65
    },
    "flagCode": "VE",
    "colors": [
      "yellow",
      "blue",
      "red"
    ],
    "availablePrompts": ["name", "flag", "location"]
  },
  {
    "country": "Virgin Islands (British)",
    "aliases": [],
    "code": "VGB",
    "capital": "Road Town",
    "location": {
      "lat": 18,
      "long": -64
    },
    "flagCode": "VG",
    "colors": [
      "blue"
    ],
    "availablePrompts": ["name", "flag", "location"]
  },
  {
    "country": "Virgin Islands (U.S.)",
    "aliases": [],
    "code": "VIR",
    "capital": "Charlotte Amalie",
    "location": {
      "lat": 18,
      "long": -64
    },
    "flagCode": "VI",
    "colors": [
      "blue"
    ],
    "availablePrompts": ["name", "flag", "location"]
  },
  {
    "country": "Vietnam",
    "aliases": [
      "Socialist Republic of Vietnam"
    ],
    "code": "VNM",
    "capital": "Hanoi",
    "location": {
      "lat": 16,
      "long": 108
    },
    "flagCode": "VN",
    "colors": [
      "red",
      "yellow"
    ],
    "availablePrompts": ["name", "flag", "location"]
  },
  {
    "country": "Vanuatu",
    "aliases": [
      "Republic of Vanuatu"
    ],
    "code": "VUT",
    "capital": "Port Vila",
    "location": {
      "lat": -17,
      "long": 168
    },
    "flagCode": "VU",
    "colors": [
      "red",
      "green",
      "black"
    ],
    "availablePrompts": ["name", "flag", "location"]
  },
  {
    "country": "Wallis and Futuna",
    "aliases": [],
    "code": "WLF",
    "capital": "Mata Utu",
    "location": {
      "lat": -13,
      "long": -176
    },
    "flagCode": "FR",
    "colors": [
      "blue",
      "white",
      "red"
    ],
    "availablePrompts": ["name", "flag", "location"]
  },
  {
    "country": "Samoa",
    "aliases": [
      "Independent State of Samoa"
    ],
    "code": "WSM",
    "capital": "Apia",
    "location": {
      "lat": -13,
      "long": -172
    },
    "flagCode": "WS",
    "colors": [
      "red",
      "blue"
    ],
    "availablePrompts": ["name", "flag", "location"]
  },
  {
    "country": "Yemen",
    "aliases": [
      "Republic of Yemen"
    ],
    "code": "YEM",
    "capital": "Sanaa",
    "location": {
      "lat": 15,
      "long": 44
    },
    "flagCode": "YE",
    "colors": [
      "red",
      "white",
      "black"
    ],
    "availablePrompts": ["name", "flag", "location"]
  },
  {
    "country": "South Africa",
    "aliases": [
      "Republic of South Africa"
    ],
    "code": "ZAF",
    "capital": "Pretoria",
    "location": {
      "lat": -30,
      "long": 25
    },
    "flagCode": "ZA",
    "colors": [
      "green",
      "red",
      "blue",
      "black"
    ],
    "availablePrompts": ["name", "flag", "location"]
  },
  {
    "country": "Zambia",
    "aliases": [
      "Republic of Zambia"
    ],
    "code": "ZMB",
    "capital": "Lusaka",
    "location": {
      "lat": -15,
      "long": 30
    },
    "flagCode": "ZM",
    "colors": [
      "green"
    ],
    "availablePrompts": ["name", "flag", "location"]
  },
  {
    "country": "Zimbabwe",
    "aliases": [
      "Republic of Zimbabwe"
    ],
    "code": "ZWE",
    "capital": "Harare",
    "location": {
      "lat": -19,
      "long": 30
    },
    "flagCode": "ZW",
    "colors": [
      "green",
      "red",
      "black",
      "yellow",
      "white"
    ],
    "availablePrompts": ["name", "flag", "location"]
  }
]